{
  "type": "GenericCrafter",
  "name": "Bio-mass-factory",
  "description": "Converts organic materials into Bio Mass.",
  "details": "Uses water, coal, and spore pods to create Bio Mass — a key ingredient for biofuel.",
  "size": 2,
  "health": 320,
  "hasLiquids": true,
  "hasItems": true,
  "hasPower": true,
  "craftTime": 60,
  "category": "crafting",
  "requirements": [
    { "item": "lead", "amount": 70 },
    { "item": "graphite", "amount": 50 },
    { "item": "titanium", "amount": 40 }
  ],
  "consumes": {
    "power": 1.2,
    "liquid": { "liquid": "water", "amount": 0.1 },
    "items": {
      "items": [
        { "item": "coal", "amount": 1 },
        { "item": "spore-pod", "amount": 2 }
      ]
    }
  },
  "outputItem": { "item": "Bio-mass", "amount": 1 },
  "craftEffect": "smeltsmoke",
  "updateEffect": "steam",
  "research": "spore-press"
}