{
  "type": "conveyor",
  "name": "Electrothermal-Conveyor",
  "description": "An advanced conveyor that uses electrical pulses to move items. Stops without power.",
  "health": 120,
  "speed": 0.28,
  "displayedSpeed": 28,
  
  // Місткість предметів
  "itemCapacity": 3,

  // Енергоспоживання
  "hasPower": true,
  "conductivePower": true,
  "consumes": {
    "power": 0.1
  },

  "requirements": [
    { "item": "Electrothermic-alloy", "amount": 1 },
    { "item": "Carbon", "amount": 2 }
  ],

  "category": "distribution",
  "research": "titanium-conveyor",

  // Ефекти іскор при роботі
  "updateEffect": "electricCharge",
  "updateEffectChance": 0.05,

  "lightColor": "a6f4ff",
  "lightRadius": 28,
  "lightOpacity": 0.55
}